pythia/__init__.py
pythia/brokers/__init__.py
pythia/brokers/base/__init__.py
pythia/brokers/base/broker.py
pythia/brokers/base/consumer.py
pythia/brokers/base/producer.py
pythia/brokers/cloud/__init__.py
pythia/brokers/cloud/aws.py
pythia/brokers/cloud/azure.py
pythia/brokers/cloud/base.py
pythia/brokers/cloud/gcp.py
pythia/brokers/database/__init__.py
pythia/brokers/database/base.py
pythia/brokers/http/__init__.py
pythia/brokers/http/base.py
pythia/brokers/http/poller.py
pythia/brokers/http/webhook_sender.py
pythia/brokers/kafka/__init__.py
pythia/brokers/kafka/admin.py
pythia/brokers/kafka/consumer.py
pythia/brokers/kafka/producer.py
pythia/brokers/rabbitmq/__init__.py
pythia/brokers/rabbitmq/consumer.py
pythia/brokers/rabbitmq/producer.py
pythia/brokers/redis/__init__.py
pythia/brokers/redis/lists.py
pythia/brokers/redis/pubsub.py
pythia/brokers/redis/streams.py
pythia/cli/__init__.py
pythia/cli/create.py
pythia/cli/monitor.py
pythia/cli/run.py
pythia/config/__init__.py
pythia/config/auto_config.py
pythia/config/base.py
pythia/config/broker_factory.py
pythia/config/cloud.py
pythia/config/http.py
pythia/config/kafka.py
pythia/config/rabbitmq.py
pythia/config/redis.py
pythia/core/__init__.py
pythia/core/lifecycle.py
pythia/core/message.py
pythia/core/worker.py
pythia/http/__init__.py
pythia/http/circuit_breaker.py
pythia/http/client.py
pythia/http/multi_poller.py
pythia/http/poller.py
pythia/http/retry.py
pythia/http/webhook.py
pythia/jobs/__init__.py
pythia/jobs/background.py
pythia/jobs/executor.py
pythia/jobs/job.py
pythia/jobs/queue.py
pythia/jobs/retry.py
pythia/jobs/scheduler.py
pythia/logging/__init__.py
pythia/logging/decorators.py
pythia/logging/formatters.py
pythia/logging/setup.py
pythia/monitoring/__init__.py
pythia/monitoring/metrics.py
pythia/monitoring/observability.py
pythia/processors/__init__.py
pythia/processors/batch.py
pythia/processors/pipeline.py
pythia/processors/single.py
pythia/processors/stream.py
pythia_framework-1.0.1.dist-info/METADATA
pythia_framework-1.0.1.dist-info/WHEEL
pythia_framework-1.0.1.dist-info/entry_points.txt
pythia_framework-1.0.1.dist-info/licenses/LICENSE
pythia_framework-1.0.1.dist-info/RECORD
