Metadata-Version: 2.4
Name: pythia-framework
Version: 1.0.1
Summary: A modern library for creating efficient and scalable workers in Python
Project-URL: Homepage, https://github.com/pythia-framework/pythia
Project-URL: Documentation, https://pythia-framework.github.io/pythia/
Project-URL: Repository, https://github.com/pythia-framework/pythia
Project-URL: Bug Tracker, https://github.com/pythia-framework/pythia/issues
Author: Pythia Contributors
Maintainer: Pythia Contributors
License-Expression: MIT
License-File: LICENSE
Keywords: async,background-jobs,distributed-systems,kafka,message-queue,microservices,rabbitmq,redis,worker
Classifier: Development Status :: 4 - Beta
Classifier: Framework :: AsyncIO
Classifier: Intended Audience :: Developers
Classifier: License :: OSI Approved :: MIT License
Classifier: Operating System :: OS Independent
Classifier: Programming Language :: Python :: 3
Classifier: Programming Language :: Python :: 3.11
Classifier: Programming Language :: Python :: 3.12
Classifier: Topic :: Communications
Classifier: Topic :: Software Development :: Libraries :: Python Modules
Classifier: Topic :: System :: Distributed Computing
Requires-Python: >=3.11
Requires-Dist: asyncio
Requires-Dist: click==8.2.1
Requires-Dist: cookiecutter==2.1.1
Requires-Dist: httpx==0.28.1
Requires-Dist: loguru==0.7.3
Requires-Dist: prometheus-client==0.22.1
Requires-Dist: psutil>=5.9.0
Requires-Dist: pydantic-settings==2.10.1
Requires-Dist: pydantic==2.11.7
Requires-Dist: rich==14.1.0
Requires-Dist: tenacity==9.1.2
Requires-Dist: watchfiles==1.1.0
Provides-Extra: all
Requires-Dist: aio-pika==9.5.7; extra == 'all'
Requires-Dist: aiosqlite>=0.20.0; extra == 'all'
Requires-Dist: azure-servicebus>=7.11.0; extra == 'all'
Requires-Dist: azure-storage-queue>=12.7.0; extra == 'all'
Requires-Dist: boto3>=1.34.0; extra == 'all'
Requires-Dist: confluent-kafka==2.11.1; extra == 'all'
Requires-Dist: datadog==0.52.1; extra == 'all'
Requires-Dist: google-cloud-pubsub>=2.18.0; extra == 'all'
Requires-Dist: newrelic==10.16.0; extra == 'all'
Requires-Dist: opentelemetry-api>=1.15.0; extra == 'all'
Requires-Dist: opentelemetry-exporter-otlp>=1.15.0; extra == 'all'
Requires-Dist: opentelemetry-exporter-prometheus<1.10.0; extra == 'all'
Requires-Dist: opentelemetry-instrumentation>=0.36b0; extra == 'all'
Requires-Dist: opentelemetry-sdk>=1.15.0; extra == 'all'
Requires-Dist: redis==6.4.0; extra == 'all'
Requires-Dist: sqlalchemy[asyncio]>=2.0.0; extra == 'all'
Provides-Extra: aws
Requires-Dist: boto3>=1.34.0; extra == 'aws'
Provides-Extra: azure
Requires-Dist: azure-servicebus>=7.11.0; extra == 'azure'
Requires-Dist: azure-storage-queue>=12.7.0; extra == 'azure'
Provides-Extra: brokers
Requires-Dist: aio-pika==9.5.7; extra == 'brokers'
Requires-Dist: confluent-kafka==2.11.1; extra == 'brokers'
Requires-Dist: redis==6.4.0; extra == 'brokers'
Provides-Extra: cloud
Requires-Dist: azure-servicebus>=7.11.0; extra == 'cloud'
Requires-Dist: azure-storage-queue>=12.7.0; extra == 'cloud'
Requires-Dist: boto3>=1.34.0; extra == 'cloud'
Requires-Dist: google-cloud-pubsub>=2.18.0; extra == 'cloud'
Provides-Extra: database
Requires-Dist: aiosqlite>=0.20.0; extra == 'database'
Requires-Dist: sqlalchemy[asyncio]>=2.0.0; extra == 'database'
Provides-Extra: gcp
Requires-Dist: google-cloud-pubsub>=2.18.0; extra == 'gcp'
Provides-Extra: kafka
Requires-Dist: confluent-kafka==2.11.1; extra == 'kafka'
Provides-Extra: monitoring
Requires-Dist: datadog==0.52.1; extra == 'monitoring'
Requires-Dist: newrelic==10.16.0; extra == 'monitoring'
Requires-Dist: opentelemetry-api>=1.15.0; extra == 'monitoring'
Requires-Dist: opentelemetry-exporter-otlp>=1.15.0; extra == 'monitoring'
Requires-Dist: opentelemetry-exporter-prometheus<1.10.0; extra == 'monitoring'
Requires-Dist: opentelemetry-instrumentation>=0.36b0; extra == 'monitoring'
Requires-Dist: opentelemetry-sdk>=1.15.0; extra == 'monitoring'
Provides-Extra: rabbitmq
Requires-Dist: aio-pika==9.5.7; extra == 'rabbitmq'
Provides-Extra: redis
Requires-Dist: redis==6.4.0; extra == 'redis'
Provides-Extra: test
Requires-Dist: coverage>=7.0.0; extra == 'test'
Requires-Dist: factory-boy>=3.3.0; extra == 'test'
Requires-Dist: freezegun>=1.2.0; extra == 'test'
Requires-Dist: pytest-asyncio>=1.1.0; extra == 'test'
Requires-Dist: pytest-benchmark>=4.0.0; extra == 'test'
Requires-Dist: pytest-clarity>=1.0.1; extra == 'test'
Requires-Dist: pytest-cov>=6.0.0; extra == 'test'
Requires-Dist: pytest-mock>=3.12.0; extra == 'test'
Requires-Dist: pytest-timeout>=2.3.0; extra == 'test'
Requires-Dist: pytest-xdist>=3.5.0; extra == 'test'
Requires-Dist: pytest>=8.4.1; extra == 'test'
Requires-Dist: responses>=0.24.0; extra == 'test'
Requires-Dist: testcontainers>=3.7.0; extra == 'test'
